VendingMachine/design.sv
// Code your design here
// the price of the product is 15 rupees and here we are using Mealy machine 
module vending_machine(
input clk,
input rst,
input [1:0] in, // 01 = 5 rs, 10 = 10 rs
output reg out,
output reg [1:0] change
);

parameter s0= 2'b00;
parameter s1 = 2'b01;
parameter s2 = 2'b10;
reg [1:0] c_state,n_state;
  
always@(posedge clk)
begin
  if(rst == 1)
    begin
      c_state = 0;
      n_state = 0;
      change =2'b00;
    end
  else
    c_state=n_state;
  case (c_state)
    s0: //state 0 : 0 rs
      if(in == 0)
        begin
          n_state= s0;
          out = 0;
          change =2'b00;
        end
      else if(in==2'b01)
        begin
          n_state =s1;
          out=0;
          change = 2'b00;
        end
      else if(in==2'b10)
        begin
         n_state =s2;
         out=0;
         change = 2'b00;
       end
     s1: //state 1 : 5 rs
       if(in == 0)
        begin
          n_state= s0;
          out = 0;
          change =2'b01; //change 5 rs
        end
      else if(in==2'b01)
        begin
          n_state =s2;
          out=0;
          change = 2'b00;
        end
      else if(in==2'b10)
        begin
         n_state =s0;
         out=1;
         change = 2'b00;
       end
     s2:
       if(in == 0)
        begin
          n_state= s0;
          out = 0;
          change =2'b10;
        end
      else if(in==2'b01)
        begin
          n_state =s0;
          out=1;
          change = 2'b00;
        end
      else if(in==2'b10)
        begin
         n_state =s0;
         out=1;
         change = 2'b01;
       end
  endcase
end
endmodule

VendingMachine/testbench.sv
// Code your testbench here
// or browse Examples
module vending_machine_tb; 
//inputs
reg clk;
reg[1:0] in;
reg rst;
  
//output
wire out;
wire [1:0] change;
vending_machine uut (
.clk (clk),
.rst (rst),
.in (in),
.out (out),
.change (change)
);
  
initial begin
//initialise inputs
  $dumpfile ("design.vcd");
  $dumpvars(0, vending_machine_tb);
rst = 1;
clk = 0;
  
#6 rst = 0;
in = 2'b01;
#11 in = 2'b01;
#16 in= 2'b01;
#25 $finish;
end
  always #5 clk=~clk;
endmodule

VendingMachine/design.vcd
$date
	Tue Jun 27 04:43:36 2023
$end
$version
	Icarus Verilog
$end
$timescale
	1s
$end
$scope module vending_machine_tb $end
$var wire 2 ! change [1:0] $end
$var wire 1 " out $end
$var reg 1 # clk $end
$var reg 2 $ in [1:0] $end
$var reg 1 % rst $end
$scope module uut $end
$var wire 1 & clk $end
$var wire 2 ' in [1:0] $end
$var wire 1 ( rst $end
$var reg 2 ) c_state [1:0] $end
$var reg 2 * change [1:0] $end
$var reg 2 + n_state [1:0] $end
$var reg 1 , out $end
$upscope $end
$upscope $end
$enddefinitions $end
#0
$dumpvars
x,
bx +
bx *
bx )
1(
bx '
0&
1%
bx $
0#
x"
bx !
$end
#5
b0 *
b0 !
b0 +
b0 )
1#
1&
#6
b1 $
b1 '
0%
0(
#10
0#
0&
#15
0,
0"
b1 +
1#
1&
#20
0#
0&
#25
b10 +
b1 )
1#
1&
#30
0#
0&
#35
1,
1"
b0 +
b10 )
1#
1&
#40
0#
0&
#45
0,
0"
b1 +
b0 )
1#
1&
#50
0#
0&
#55
b10 +
b1 )
1#
1&
